{
  "secid": "secid:regulation/ca.gov/sb-1001-bot-disclosure",
  "name": "California state legislation: Sb 1001 Bot Disclosure",
  "version": "",
  "owner": "California State Government",
  "type": "Regulation",
  "description": "California state legislation: Sb 1001 Bot Disclosure",
  "relationToCloudSecurity": "",
  "relationToAISecurity": "",
  "license": {
    "spdx": "Unlicense",
    "redistribution": "permitted",
    "derivatives": "permitted",
    "publicly_redistributable": true,
    "license_text_url": "https://www.usa.gov/government-copyright",
    "notes": "Work of the US government is in the public domain in the United States per 17 U.S.C. \u00a7 105. State and local government works generally follow the same convention but may vary; consult the specific issuer for definitive terms."
  },
  "links": {
    "source": "https://leginfo.legislature.ca.gov/faces/billNavClient.xhtml?bill_id=201720180SB1001",
    "csaLocation": "",
    "source_research_note": "California SB-1001 Bolstering Online Transparency Act (Bot Disclosure, 2018).",
    "acquisition_status": "acquired"
  },
  "lifecycle": {
    "active": true,
    "supersedes": "",
    "supersededBy": null,
    "retiredFromActiveUse": null,
    "notes": ""
  },
  "notes": "Auto-generated bulk metadata. Enrich title/description/relations as needed.",
  "desired_end_state": {
    "state": "extracted",
    "reason": "policy-doc"
  },
  "current_extraction": {
    "s3_timestamp": "2026-05-21T18:33:33Z",
    "tool": "curl + tools-resources/utils/convert-HTML-to-Markdown.py",
    "notes": "Acquired the SB-1001 bill landing page from leginfo.legislature.ca.gov. 180 lines covering metadata, status, and votes. Bill text at the 'Text' link \u2014 same follow-up pattern as SB-1120."
  }
}
